{
    "android_gradle_plugin_version": "2.3.3",
    "apk_path": "/Users/fangtao/Android Studio Project/aarTest/app/build/outputs/apk/app-debug.apk",
    "apt": {
        
    },
    "apt_libraries": {
        "dagger": false,
        "butterknife": false
    },
    "auto_dependency": true,
    "build_cache_dir": "/Users/fangtao/Android Studio Project/aarTest/app/build/freeline",
    "build_directory": "/Users/fangtao/Android Studio Project/aarTest/app/build",
    "build_script": "./gradlew :app:assembleDebug",
    "build_script_work_directory": "",
    "build_tools_directory": "/Users/fangtao/Library/Android/sdk/build-tools/25.0.3",
    "build_tools_version": "25.0.3",
    "check_sources_md5": [
        
    ],
    "compile_sdk_directory": "/Users/fangtao/Library/Android/sdk/platforms/android-25",
    "compile_sdk_version": "android-25",
    "databinding": [
        
    ],
    "databinding_compiler_jar": "",
    "databinding_modules": [
        
    ],
    "debug_package": "com.fangtao.aartest",
    "exclude_dep_res_paths": [
        
    ],
    "extra_dep_res_paths": [
        
    ],
    "freeline_cache_dir": "/Users/fangtao/Android Studio Project/aarTest",
    "freeline_gradle_plugin_version": "0.8.7",
    "ignore_resource_ids": [
        "avd_hide_password_1",
        "avd_hide_password_2",
        "avd_hide_password_3",
        "avd_show_password_1",
        "avd_show_password_2",
        "avd_show_password_3"
    ],
    "java_home": "/Library/Java/JavaVirtualMachines/jdk1.8.0_51.jdk/Contents/Home",
    "launcher": "com.fangtao.aartest.MainActivity",
    "main_assets_directory": [
        "/Users/fangtao/Android Studio Project/aarTest/app/src/debug/assets",
        "/Users/fangtao/Android Studio Project/aarTest/app/src/main/assets"
    ],
    "main_jniLibs_directory": [
        "/Users/fangtao/Android Studio Project/aarTest/app/src/debug/jniLibs",
        "/Users/fangtao/Android Studio Project/aarTest/app/src/main/jniLibs"
    ],
    "main_jni_directory": [
        "/Users/fangtao/Android Studio Project/aarTest/app/src/debug/jni",
        "/Users/fangtao/Android Studio Project/aarTest/app/src/main/jni"
    ],
    "main_manifest_path": "/Users/fangtao/Android Studio Project/aarTest/app/src/main/AndroidManifest.xml",
    "main_project_dir": "app",
    "main_project_name": "app",
    "main_r_path": "/Users/fangtao/Android Studio Project/aarTest/app/build/generated/source/r/debug/R.java",
    "main_res_directory": [
        "/Users/fangtao/Android Studio Project/aarTest/app/src/debug/res",
        "/Users/fangtao/Android Studio Project/aarTest/app/src/main/res"
    ],
    "main_src_directory": [
        "/Users/fangtao/Android Studio Project/aarTest/app/src/debug/java",
        "/Users/fangtao/Android Studio Project/aarTest/app/src/main/java"
    ],
    "module_dependencies": {
        "app": [
            "ftlibrary"
        ],
        "ftlibrary": [
            
        ]
    },
    "modules": [
        {
            "name": "app",
            "path": "/Users/fangtao/Android Studio Project/aarTest/app"
        },
        {
            "name": "ftlibrary",
            "path": "/Users/fangtao/Android Studio Project/aarTest/ftlibrary"
        }
    ],
    "package": "com.fangtao.aartest",
    "product_flavor": "",
    "project_source_sets": {
        "app": {
            "main_assets_directory": [
                "/Users/fangtao/Android Studio Project/aarTest/app/src/debug/assets",
                "/Users/fangtao/Android Studio Project/aarTest/app/src/main/assets"
            ],
            "main_jniLibs_directory": [
                "/Users/fangtao/Android Studio Project/aarTest/app/src/debug/jniLibs",
                "/Users/fangtao/Android Studio Project/aarTest/app/src/main/jniLibs"
            ],
            "main_jni_directory": [
                "/Users/fangtao/Android Studio Project/aarTest/app/src/debug/jni",
                "/Users/fangtao/Android Studio Project/aarTest/app/src/main/jni"
            ],
            "main_manifest_path": "/Users/fangtao/Android Studio Project/aarTest/app/src/main/AndroidManifest.xml",
            "main_res_directory": [
                "/Users/fangtao/Android Studio Project/aarTest/app/src/debug/res",
                "/Users/fangtao/Android Studio Project/aarTest/app/src/main/res"
            ],
            "main_src_directory": [
                "/Users/fangtao/Android Studio Project/aarTest/app/src/debug/java",
                "/Users/fangtao/Android Studio Project/aarTest/app/src/main/java"
            ]
        },
        "ftlibrary": {
            "main_assets_directory": [
                "/Users/fangtao/Android Studio Project/aarTest/ftlibrary/src/release/assets",
                "/Users/fangtao/Android Studio Project/aarTest/ftlibrary/src/main/assets"
            ],
            "main_jniLibs_directory": [
                "/Users/fangtao/Android Studio Project/aarTest/ftlibrary/src/release/jniLibs",
                "/Users/fangtao/Android Studio Project/aarTest/ftlibrary/src/main/jniLibs"
            ],
            "main_jni_directory": [
                "/Users/fangtao/Android Studio Project/aarTest/ftlibrary/src/release/jni",
                "/Users/fangtao/Android Studio Project/aarTest/ftlibrary/src/main/jni"
            ],
            "main_manifest_path": "/Users/fangtao/Android Studio Project/aarTest/ftlibrary/src/main/AndroidManifest.xml",
            "main_res_directory": [
                "/Users/fangtao/Android Studio Project/aarTest/ftlibrary/src/release/res",
                "/Users/fangtao/Android Studio Project/aarTest/ftlibrary/src/main/res"
            ],
            "main_src_directory": [
                "/Users/fangtao/Android Studio Project/aarTest/ftlibrary/src/release/java",
                "/Users/fangtao/Android Studio Project/aarTest/ftlibrary/src/main/java"
            ]
        }
    },
    "project_type": "gradle",
    "retrolambda": {
        
    },
    "root_dir": "/Users/fangtao/Android Studio Project/aarTest",
    "sdk_directory": "/Users/fangtao/Library/Android/sdk",
    "use_jdk8": true,
    "use_system_gradle": false
}